pyawsopstoolkit_advsearch/__globals__.py
pyawsopstoolkit_advsearch/__init__.py
pyawsopstoolkit_advsearch/__validations__.py
pyawsopstoolkit_advsearch/ec2.py
pyawsopstoolkit_advsearch/exceptions.py
pyawsopstoolkit_advsearch/iam.py
pyawsopstoolkit_advsearch/search.py
pyawsopstoolkit_advsearch-0.1.1.dist-info/LICENSE
pyawsopstoolkit_advsearch-0.1.1.dist-info/METADATA
pyawsopstoolkit_advsearch-0.1.1.dist-info/WHEEL
pyawsopstoolkit_advsearch-0.1.1.dist-info/top_level.txt
pyawsopstoolkit_advsearch-0.1.1.dist-info/RECORD
