Metadata-Version: 2.1
Name: pyawsopstoolkit-advsearch
Version: 0.1.1
Summary: This package delivers an exhaustive array of advanced search functionalities tailor-made for seamless integration with
Home-page: https://github.com/coldsofttech/pyawsopstoolkit-advsearch.git
Author: coldsofttech
License: MIT
Keywords: aws,toolkit,operations,tools,development,python,search,utilities,amazon-web-services,advance-search,search-functionality
Classifier: Development Status :: 4 - Beta
Classifier: Intended Audience :: Developers
Classifier: Topic :: Software Development :: Libraries
Classifier: Topic :: Software Development :: Libraries :: Python Modules
Classifier: License :: OSI Approved :: MIT License
Classifier: Programming Language :: Python :: 3.10
Classifier: Programming Language :: Python :: 3.11
Classifier: Programming Language :: Python :: 3.12
License-File: LICENSE
Requires-Dist: pyawsopstoolkit==0.1.19
Requires-Dist: pyawsopstoolkit-models==0.1.1
Requires-Dist: botocore==1.34.158
